[
	{
		"Path": "/"
		, "Controller": "Home\\HomeController"
		, "Action": "Display"
		, "Name": "DisplayHome"
	}
	, {
		"Path": "/Contact"
		, "Controller": "Contact\\ContactController"
		, "Action": "Display"
		, "Name": "DisplayContact"
	}
	, {
		"Path": "/Contact/Send"
		, "Controller": "Contact\\ContactController"
		, "Action": "Send"
		, "Name": "ContactSend"
	}
	, {
		"Path": "/Admin"
		, "Controller": "Admin\\AdminController"
		, "Action": "Display"
		, "Name": "DisplayAdmin"
	}
	, {
		"Path": "/Admin/Post"
		, "Controller": "Post\\PostController"
		, "Action": "DisplayAllAsTable"
		, "Name": "DisplayAllPostAsTable"
	}
	, {
		"Path": "/Admin/Post/Add"
		, "Controller": "Post\\PostController"
		, "Action": "Add"
		, "Name": "AddPost"
	}
	, {
		"Path": "/Admin/User/Login"
		, "Controller": "Admin\\User\\UserController"
		, "Action": "Login"
		, "Name": "UserLoginAdmin"
	}
	, {
		"Path": "/Admin/User/Logout"
		, "Controller": "Admin\\User\\UserController"
		, "Action": "Logout"
		, "Name": "UserLogoutAdmin"
	}
	, {
		"Path": "/Policy/Privacy"
		, "Controller": "Policy\\PrivacyController"
		, "Action": "Display"
		, "Name": "DisplayPrivacy"
	}
	, {
		"Path": "/Policy/Terms"
		, "Controller": "Policy\\TermsController"
		, "Action": "Display"
		, "Name": "DisplayTerms"
	}
	, {
		"Path": "/Error"
		, "Controller": "Error\\ErrorController"
		, "Action": "Display"
		, "Name": "DisplayError"
	}
]